hotsoss/__init__.py
hotsoss/crossdispersion.py
hotsoss/locate_trace.py
hotsoss/plotting.py
hotsoss/utils.py
hotsoss/files/.DS_Store
hotsoss/files/GR700XD_1.txt
hotsoss/files/GR700XD_2.txt
hotsoss/files/GR700XD_3.txt
hotsoss/files/WASP107b_pandexo_input_spectrum.dat
hotsoss/files/extracted_spectra.png
hotsoss/files/gr700xd_clear_order1.dat
hotsoss/files/gr700xd_clear_order2.dat
hotsoss/files/gr700xd_clear_order3.dat
hotsoss/files/gr700xd_f277w_order1.dat
hotsoss/files/niriss_ref_photom.fits
hotsoss/files/order1_trace.txt
hotsoss/files/order2_trace.txt
hotsoss/files/order3_trace.txt
hotsoss/files/order_masks.npy
hotsoss/files/scaled_spectrum.txt
hotsoss/files/soss_wavelength_trace_table1.txt
hotsoss/files/soss_wavelengths_fullframe.fits
hotsoss/files/wavelength_bins.npy
hotsoss-0.1.10.dist-info/AUTHORS.rst
hotsoss-0.1.10.dist-info/LICENSE
hotsoss-0.1.10.dist-info/METADATA
hotsoss-0.1.10.dist-info/WHEEL
hotsoss-0.1.10.dist-info/top_level.txt
hotsoss-0.1.10.dist-info/RECORD
