Metadata-Version: 2.1
Name: hotsoss
Version: 0.1.10
Summary: Helpful Organizational Tools for SOSS
Home-page: https://github.com/hover2pi/hotsoss
Author: Joe Filippazzo
Author-email: jfilippazzo@stsci.edu
License: MIT license
Keywords: hotsoss
Classifier: Development Status :: 2 - Pre-Alpha
Classifier: Intended Audience :: Developers
Classifier: License :: OSI Approved :: MIT License
Classifier: Natural Language :: English
Classifier: Programming Language :: Python :: 3.10
Classifier: Programming Language :: Python :: 3.11
License-File: LICENSE
License-File: AUTHORS.rst
Requires-Dist: numpy
Requires-Dist: astropy
Requires-Dist: bokeh
Requires-Dist: scipy
